moss.py
pymoss-0.2.dist-info/LICENSE
pymoss-0.2.dist-info/METADATA
pymoss-0.2.dist-info/WHEEL
pymoss-0.2.dist-info/top_level.txt
pymoss-0.2.dist-info/RECORD
